resultdownloader/__init__.py
resultdownloader/cli.py
resultdownloader/downloader.py
resultdownloader-1.0.1.dist-info/WHEEL
resultdownloader-1.0.1.dist-info/entry_points.txt
resultdownloader-1.0.1.dist-info/METADATA
resultdownloader-1.0.1.dist-info/RECORD
