Metadata-Version: 2.3
Name: resultdownloader
Version: 1.0.1
Summary: Downloads results from RaceTimePro
Requires-Dist: bs4>=0.0.2
Requires-Dist: lxml>=6.0.2
Requires-Dist: pandas>=2.3.3
Requires-Dist: requests>=2.32.5
Requires-Python: >=3.10
